cli/__init__.py
cli/config.py
cli/i18n.py
cli/interactive.py
cli/main.py
cli/modules.py
cli/params.py
cli/runner.py
cli/ui.py
cli/workflow.py
core/__init__.py
core/constants.py
core/mcp_server.py
core/utils.py
core/analysis/__init__.py
core/analysis/html_analyzer.py
core/api/__init__.py
core/api/plugins/__init__.py
core/api/plugins/routes.py
core/api/plugins/service.py
core/browser/__init__.py
core/browser/driver.py
core/catalog/__init__.py
core/catalog/category.py
core/catalog/module.py
core/catalog/outline.py
core/engine/__init__.py
core/engine/exceptions.py
core/engine/flow_control.py
core/engine/step_executor.py
core/engine/trace.py
core/engine/variable_resolver.py
core/engine/breakpoints/__init__.py
core/engine/breakpoints/manager.py
core/engine/breakpoints/models.py
core/engine/breakpoints/store.py
core/engine/context/__init__.py
core/engine/context/layers.py
core/engine/evidence/__init__.py
core/engine/evidence/executor_hooks.py
core/engine/evidence/hook.py
core/engine/evidence/models.py
core/engine/evidence/store.py
core/engine/hooks/__init__.py
core/engine/hooks/base.py
core/engine/hooks/implementations.py
core/engine/hooks/models.py
core/engine/introspection/__init__.py
core/engine/introspection/autocomplete.py
core/engine/introspection/catalog.py
core/engine/lineage/__init__.py
core/engine/lineage/analysis.py
core/engine/lineage/context.py
core/engine/lineage/models.py
core/engine/lineage/tracker.py
core/engine/replay/__init__.py
core/engine/replay/manager.py
core/engine/replay/models.py
core/engine/sdk/__init__.py
core/engine/sdk/interface.py
core/engine/sdk/models.py
core/engine/sdk/resolver.py
core/engine/step_executor/__init__.py
core/engine/step_executor/context_builder.py
core/engine/step_executor/executor.py
core/engine/step_executor/foreach.py
core/engine/step_executor/retry.py
core/engine/workflow/__init__.py
core/engine/workflow/debug.py
core/engine/workflow/engine.py
core/engine/workflow/output.py
core/engine/workflow/routing.py
flyto_core-2.0.3.dist-info/licenses/LICENSE
flyto_core-2.0.3.dist-info/licenses/LICENSE-COMMERCIAL.md
flyto_core-2.0.3.dist-info/licenses/LICENSE-HEADER.txt
flyto_core-2.0.3.dist-info/licenses/NOTICE
flyto_core-2.0.3.dist-info/METADATA
flyto_core-2.0.3.dist-info/WHEEL
flyto_core-2.0.3.dist-info/entry_points.txt
flyto_core-2.0.3.dist-info/top_level.txt
flyto_core-2.0.3.dist-info/RECORD
