Metadata-Version: 2.4
Name: flyto-core
Version: 2.0.3
Summary: Atomic workflow automation modules for git-native automation
Author-email: Flyto Team <team@flyto.dev>
Maintainer-email: Flyto Team <team@flyto.dev>
License: Source Available License v1.0
Project-URL: Homepage, https://github.com/flytohub/flyto-core
Project-URL: Documentation, https://github.com/flytohub/flyto-core#readme
Project-URL: Repository, https://github.com/flytohub/flyto-core.git
Project-URL: Issues, https://github.com/flytohub/flyto-core/issues
Project-URL: Changelog, https://github.com/flytohub/flyto-core/blob/main/CHANGELOG.md
Keywords: automation,workflow,atomic-modules,web-scraping,browser-automation
Classifier: Development Status :: 4 - Beta
Classifier: Intended Audience :: Developers
Classifier: Operating System :: OS Independent
Classifier: Programming Language :: Python :: 3
Classifier: Programming Language :: Python :: 3.9
Classifier: Programming Language :: Python :: 3.10
Classifier: Programming Language :: Python :: 3.11
Classifier: Programming Language :: Python :: 3.12
Classifier: Topic :: Software Development :: Libraries :: Python Modules
Classifier: Topic :: Internet :: WWW/HTTP :: Browsers
Classifier: Framework :: AsyncIO
Requires-Python: >=3.9
License-File: LICENSE
License-File: LICENSE-COMMERCIAL.md
License-File: LICENSE-HEADER.txt
License-File: NOTICE
Requires-Dist: pyyaml>=6.0
Requires-Dist: aiohttp>=3.9.0
Requires-Dist: beautifulsoup4>=4.12.0
Requires-Dist: lxml>=4.9.0
Requires-Dist: pydantic>=2.0.0
Requires-Dist: python-dotenv>=1.0.0
Requires-Dist: aiofiles>=23.0.0
Provides-Extra: browser
Requires-Dist: playwright>=1.40.0; extra == "browser"
Provides-Extra: api
Requires-Dist: fastapi>=0.104.0; extra == "api"
Requires-Dist: uvicorn>=0.24.0; extra == "api"
Provides-Extra: vector
Requires-Dist: qdrant-client>=1.7.0; extra == "vector"
Requires-Dist: sentence-transformers>=2.2.0; extra == "vector"
Provides-Extra: telegram
Requires-Dist: python-telegram-bot>=20.0; extra == "telegram"
Provides-Extra: all
Requires-Dist: flyto-core[api,browser,telegram,vector]; extra == "all"
Provides-Extra: dev
Requires-Dist: pytest>=7.4.0; extra == "dev"
Requires-Dist: pytest-asyncio>=0.21.0; extra == "dev"
Requires-Dist: pytest-cov>=4.1.0; extra == "dev"
Requires-Dist: black>=23.0.0; extra == "dev"
Requires-Dist: ruff>=0.1.0; extra == "dev"
Requires-Dist: mypy>=1.0.0; extra == "dev"
Requires-Dist: build>=1.0.0; extra == "dev"
Requires-Dist: twine>=4.0.0; extra == "dev"
Dynamic: license-file
